<?xml version="1.0"?>
<pkg-contents spec="1.12">
  <f n="json-c-install" o="root" g="staff" p="16877" pt="json-c-install" m="false" t="file">
    <f n="usr" o="root" g="wheel" p="16877">
      <f n="local" o="root" g="wheel" p="16893">
        <f n="include" o="root" g="wheel" p="16893">
          <f n="json" o="root" g="wheel" p="16893">
            <f n="arraylist.h" o="root" g="wheel" p="33204">
              <mod>mode</mod>
            </f>
            <f n="bits.h" o="root" g="wheel" p="33204">
              <mod>mode</mod>
            </f>
            <f n="debug.h" o="root" g="wheel" p="33204">
              <mod>mode</mod>
            </f>
            <f n="json.h" o="root" g="wheel" p="33204">
              <mod>mode</mod>
            </f>
            <f n="json_object.h" o="root" g="wheel" p="33204">
              <mod>mode</mod>
            </f>
            <f n="json_object_private.h" o="root" g="wheel" p="33204">
              <mod>mode</mod>
            </f>
            <f n="json_tokener.h" o="root" g="wheel" p="33204">
              <mod>mode</mod>
            </f>
            <f n="json_util.h" o="root" g="wheel" p="33204">
              <mod>mode</mod>
            </f>
            <f n="linkhash.h" o="root" g="wheel" p="33204">
              <mod>mode</mod>
            </f>
            <f n="printbuf.h" o="root" g="wheel" p="33204">
              <mod>mode</mod>
            </f>
            <mod>mode</mod>
          </f>
        </f>
        <f n="lib" o="root" g="wheel" p="16893">
          <f n="libjson.0.dylib" o="root" g="wheel" p="33277">
            <mod>mode</mod>
          </f>
          <f n="libjson.a" o="root" g="wheel" p="33204">
            <mod>mode</mod>
          </f>
          <f n="libjson.dylib" o="root" g="wheel" p="41469">
            <mod>mode</mod>
          </f>
          <f n="libjson.la" o="root" g="wheel" p="33277">
            <mod>mode</mod>
          </f>
          <f n="pkgconfig" o="root" g="wheel" p="16893">
            <f n="json.pc" o="root" g="wheel" p="33204">
              <mod>mode</mod>
            </f>
          </f>
        </f>
        <f n="share" o="root" g="wheel" p="16893">
          <f n="doc" o="root" g="wheel" p="16893">
            <f n="json-c" o="root" g="wheel" p="16893">
              <f n="AUTHORS" o="root" g="wheel" p="33204">
                <mod>mode</mod>
              </f>
              <f n="ChangeLog" o="root" g="wheel" p="33204">
                <mod>mode</mod>
              </f>
              <f n="COPYING" o="root" g="wheel" p="33204">
                <mod>mode</mod>
              </f>
              <f n="INSTALL" o="root" g="wheel" p="33204">
                <mod>mode</mod>
              </f>
              <f n="NEWS" o="root" g="wheel" p="33204">
                <mod>mode</mod>
              </f>
              <f n="README" o="root" g="wheel" p="33204">
                <mod>mode</mod>
              </f>
              <f n="README-WIN32.html" o="root" g="wheel" p="33204">
                <mod>mode</mod>
              </f>
              <f n="README.html" o="root" g="wheel" p="33204">
                <mod>mode</mod>
              </f>
              <mod>mode</mod>
            </f>
          </f>
        </f>
      </f>
    </f>
  </f>
</pkg-contents>
